django_sequence/__init__.py
django_sequence/admin.py
django_sequence/fields.py
django_sequence/models.py
django_sequence/migrations/0001_initial.py
django_sequence/migrations/0002_populate.py
django_sequence/migrations/0003_alter_sequence_id_alter_stage_id_and_more.py
django_sequence/migrations/__init__.py
django_sequence-0.0.0.dist-info/LICENSE
django_sequence-0.0.0.dist-info/METADATA
django_sequence-0.0.0.dist-info/WHEEL
django_sequence-0.0.0.dist-info/top_level.txt
django_sequence-0.0.0.dist-info/zip-safe
django_sequence-0.0.0.dist-info/RECORD
