Metadata-Version: 2.1
Name: django-sequence
Version: 0.0.0
Home-page: https://github.com/davidslusser/django-sequences
Author: David Slusser
Author-email: dbslusser@gmail.com
License: GNU
Platform: any
License-File: LICENSE
Requires-Dist: Django
Provides-Extra: dev
Requires-Dist: bandit (~=1.7) ; extra == 'dev'
Requires-Dist: black (~=22.3) ; extra == 'dev'
Requires-Dist: build (~=0.8) ; extra == 'dev'
Requires-Dist: flake9 ; extra == 'dev'
Requires-Dist: mypy ; extra == 'dev'
Requires-Dist: pylint (~=2.14) ; extra == 'dev'
Requires-Dist: pytest (~=7.1) ; extra == 'dev'
Requires-Dist: pytest-cov (~=3.0) ; extra == 'dev'
